[
    {
        "user_name": "Concurrent Test User",
        "month": 1,
        "income": {
            "salary": 75000.0,
            "investments": 0,
            "other": 0,
            "total": 75000.0
        },
        "expenses": {
            "housing": 2000.0,
            "utilities": 0,
            "groceries": 800.0,
            "transportation": 500.0,
            "healthcare": 0,
            "entertainment": 0,
            "dining_out": 0,
            "subscriptions": 0,
            "other": 0,
            "total": 3300.0
        },
        "balance": {
            "starting": 0,
            "ending": 71700.0,
            "change": 71700.0
        }
    },
    {
        "month": 2,
        "timestamp": "2025-06-24T14:56:17.948487",
        "user_name": "Concurrent Test User",
        "income": {
            "salary": 75000.0,
            "investments": 0,
            "other": 0,
            "total": 75000.0
        },
        "expenses": {
            "housing": 0,
            "utilities": 0,
            "groceries": 0,
            "transportation": 0,
            "healthcare": 0,
            "entertainment": 0,
            "dining_out": 0,
            "subscriptions": 0,
            "other": 0,
            "total": 3300.0
        },
        "savings": {
            "amount": 71700.0,
            "percentage_of_income": 95.6,
            "target_met": false
        },
        "balance": {
            "starting": 0,
            "ending": 71700.0,
            "change": 71700.0
        },
        "analysis": {
            "spending_categories": {
                "essential": 0,
                "non_essential": 0,
                "ratio": 0
            },
            "savings_rate": "N/A",
            "cash_flow": "Neutral"
        },
        "notes": "This is a minimal report based on your provided data."
    },
    {
        "month": 3,
        "timestamp": "2025-06-24T14:58:55.512513",
        "user_name": "Concurrent Test User",
        "income": {
            "salary": 75000.0,
            "investments": 0,
            "other": 0,
            "total": 75000.0
        },
        "expenses": {
            "housing": 0,
            "utilities": 0,
            "groceries": 0,
            "transportation": 0,
            "healthcare": 0,
            "entertainment": 0,
            "dining_out": 0,
            "subscriptions": 0,
            "other": 0,
            "total": 3300.0
        },
        "savings": {
            "amount": 71700.0,
            "percentage_of_income": 95.6,
            "target_met": false
        },
        "balance": {
            "starting": 0,
            "ending": 71700.0,
            "change": 71700.0
        },
        "analysis": {
            "spending_categories": {
                "essential": 0,
                "non_essential": 0,
                "ratio": 0
            },
            "savings_rate": "N/A",
            "cash_flow": "Neutral"
        },
        "notes": "This is a minimal report based on your provided data."
    },
    {
        "month": 4,
        "timestamp": "2025-06-24T15:00:47.109736",
        "user_name": "Concurrent Test User",
        "income": {
            "salary": 75000.0,
            "investments": 0,
            "other": 0,
            "total": 75000.0
        },
        "expenses": {
            "housing": 0,
            "utilities": 0,
            "groceries": 0,
            "transportation": 0,
            "healthcare": 0,
            "entertainment": 0,
            "dining_out": 0,
            "subscriptions": 0,
            "other": 0,
            "total": 3300.0
        },
        "savings": {
            "amount": 71700.0,
            "percentage_of_income": 95.6,
            "target_met": false
        },
        "balance": {
            "starting": 0,
            "ending": 71700.0,
            "change": 71700.0
        },
        "analysis": {
            "spending_categories": {
                "essential": 0,
                "non_essential": 0,
                "ratio": 0
            },
            "savings_rate": "N/A",
            "cash_flow": "Neutral"
        },
        "notes": "This is a minimal report based on your provided data."
    },
    {
        "month": 5,
        "timestamp": "2025-07-24T15:00:47.109736",
        "user_name": "Concurrent Test User",
        "income": {
            "salary": 75000.0,
            "investments": 0,
            "other": 0,
            "total": 75000.0
        },
        "expenses": {
            "housing": 0,
            "utilities": 0,
            "groceries": 0,
            "transportation": 0,
            "healthcare": 0,
            "entertainment": 0,
            "dining_out": 0,
            "subscriptions": 0,
            "other": 0,
            "total": 3300.0
        },
        "savings": {
            "amount": 71670.0,
            "percentage_of_income": 95.56,
            "target_met": false
        },
        "balance": {
            "starting": 71700.0,
            "ending": 143370.0,
            "change": 71670.0
        },
        "analysis": {
            "spending_categories": {
                "essential": 0,
                "non_essential": 0,
                "ratio": 0
            },
            "savings_rate": "Excellent",
            "cash_flow": "Positive"
        },
        "notes": "You've maintained a high savings rate, but consider allocating some funds to essential expenses like housing and utilities to ensure a balanced financial plan."
    },
    {
        "month": 6,
        "timestamp": "2025-06-24T15:04:57.504961",
        "user_name": "Concurrent Test User",
        "income": {
            "salary": 75000.0,
            "investments": 0,
            "other": 0,
            "total": 75000.0
        },
        "expenses": {
            "housing": 0,
            "utilities": 0,
            "groceries": 0,
            "transportation": 0,
            "healthcare": 0,
            "entertainment": 0,
            "dining_out": 0,
            "subscriptions": 0,
            "other": 0,
            "total": 3300.0
        },
        "savings": {
            "amount": 71700.0,
            "percentage_of_income": 95.6,
            "target_met": false
        },
        "balance": {
            "starting": 0,
            "ending": 71700.0,
            "change": 71700.0
        },
        "analysis": {
            "spending_categories": {
                "essential": 0,
                "non_essential": 0,
                "ratio": 0
            },
            "savings_rate": "N/A",
            "cash_flow": "Neutral"
        },
        "notes": "This is a minimal report based on your provided data."
    }
]