[
    {
        "user_name": "hello ",
        "month": 1,
        "income": {
            "salary": 6000.0,
            "investments": 0,
            "other": 0,
            "total": 6000.0
        },
        "expenses": {
            "housing": 0,
            "utilities": 0,
            "groceries": 0,
            "transportation": 0,
            "healthcare": 0,
            "entertainment": 0,
            "dining_out": 0,
            "subscriptions": 0,
            "other": 20.0,
            "total": 20.0
        },
        "balance": {
            "starting": 0,
            "ending": 5980.0,
            "change": 5980.0
        }
    },
    {
        "user_name": "hello ",
        "month": 2,
        "income": {
            "salary": 6000.0,
            "investments": 0,
            "other": 0,
            "total": 6000.0
        },
        "expenses": {
            "housing": 0,
            "utilities": 0,
            "groceries": 0,
            "transportation": 0,
            "healthcare": 0,
            "entertainment": 0,
            "dining_out": 0,
            "subscriptions": 0,
            "other": 20.0,
            "total": 20.0
        },
        "balance": {
            "starting": 5980.0,
            "ending": 11960.0,
            "change": 5980.0
        },
        "notes": "Based on last month's data, it seems like you have a good handle on your expenses. Consider allocating some of your income towards savings or investments to reach your financial goal.",
        "savings": 11940.0,
        "recommendations": [
            "Consider opening a savings account to reach your financial goal",
            "Review your budget to see if there are any areas where you can cut back on unnecessary expenses"
        ]
    },
    {
        "user_name": "hello ",
        "month": 3,
        "income": {
            "salary": 6000.0,
            "investments": 0,
            "other": 0,
            "total": 6000.0
        },
        "expenses": {
            "housing": 0,
            "utilities": 0,
            "groceries": 0,
            "transportation": 0,
            "healthcare": 0,
            "entertainment": 0,
            "dining_out": 0,
            "subscriptions": 0,
            "other": 20.0,
            "total": 20.0
        },
        "balance": {
            "starting": 11960.0,
            "ending": 17940.0,
            "change": 5980.0
        },
        "notes": "Great job on maintaining a consistent income and low expenses! Consider allocating more towards savings and investments to reach your financial goal.",
        "savings": 17920.0,
        "recommendations": [
            "Increase savings by 10% each month to reach your financial goal",
            "Explore low-risk investment options to diversify your portfolio"
        ]
    },
    {
        "user_name": "hello ",
        "month": 4,
        "income": {
            "salary": 6000.0,
            "investments": 0,
            "other": 0,
            "total": 6000.0
        },
        "expenses": {
            "housing": 0,
            "utilities": 0,
            "groceries": 0,
            "transportation": 0,
            "healthcare": 0,
            "entertainment": 0,
            "dining_out": 0,
            "subscriptions": 0,
            "other": 20.0,
            "total": 20.0
        },
        "balance": {
            "starting": 17940.0,
            "ending": 23940.0,
            "change": 6000.0
        },
        "notes": "You've maintained a consistent income and low expenses. Consider increasing your savings rate to 15% to reach your financial goal faster.",
        "savings": 23920.0,
        "recommendations": [
            "Increase savings by 15% each month to reach your financial goal",
            "Explore low-risk investment options to diversify your portfolio",
            "Consider allocating a small portion of your income towards entertainment to maintain a healthy work-life balance"
        ]
    },
    {
        "user_name": "hello ",
        "month": 5,
        "income": {
            "salary": 6000.0,
            "investments": 0,
            "other": 0,
            "total": 6000.0
        },
        "expenses": {
            "housing": 0,
            "utilities": 0,
            "groceries": 0,
            "transportation": 0,
            "healthcare": 0,
            "entertainment": 0,
            "dining_out": 0,
            "subscriptions": 0,
            "other": 20.0,
            "total": 20.0
        },
        "balance": {
            "starting": 23940.0,
            "ending": 29940.0,
            "change": 6000.0
        },
        "notes": "You've maintained a consistent income and low expenses. Consider increasing your savings rate to 20% to reach your financial goal faster.",
        "savings": 29920.0,
        "recommendations": [
            "Increase savings by 20% each month to reach your financial goal",
            "Explore low-risk investment options to diversify your portfolio",
            "Consider allocating a small portion of your income towards entertainment to maintain a healthy work-life balance",
            "Review your budget to identify areas where you can cut back on unnecessary expenses"
        ]
    },
    {
        "user_name": "hello ",
        "month": 6,
        "income": {
            "salary": 6000.0,
            "investments": 0,
            "other": 0,
            "total": 6000.0
        },
        "expenses": {
            "housing": 0,
            "utilities": 0,
            "groceries": 0,
            "transportation": 0,
            "healthcare": 0,
            "entertainment": 0,
            "dining_out": 0,
            "subscriptions": 0,
            "other": 20.0,
            "total": 20.0
        },
        "balance": {
            "starting": 29940.0,
            "ending": 35940.0,
            "change": 6000.0
        },
        "notes": "You've maintained a consistent income and low expenses. Consider increasing your savings rate to 25% to reach your financial goal faster. You've shown good discipline in keeping expenses low, but don't forget to allocate some funds for entertainment to maintain a healthy work-life balance.",
        "savings": 35920.0,
        "recommendations": [
            "Increase savings by 25% each month to reach your financial goal",
            "Explore low-risk investment options to diversify your portfolio",
            "Allocate a small portion of your income towards entertainment to maintain a healthy work-life balance",
            "Review your budget to identify areas where you can cut back on unnecessary expenses and allocate those funds towards savings"
        ]
    }
]